lighttext/__init__.py
lighttext/component/__init__.py
lighttext/component/article.py
lighttext/component/character.py
lighttext/component/paragraph.py
lighttext/component/sentence.py
lighttext/component/vocabulary.py
lighttext/component/word.py
lighttext/data/ban.txt
lighttext/data/dict.txt
lighttext/data/post_filter_pos.txt
lighttext/data/pre_filter_pos.txt
lighttext/data/stopwords.txt
lighttext/string_search/__init__.py
lighttext/string_search/ac.py
lighttext/string_search/keyword.py
lighttext/string_search/ner.py
lighttext/text_mining/__init__.py
lighttext/text_mining/new_words_detection/__init__.py
lighttext/text_mining/new_words_detection/detector.py
lighttext/text_mining/new_words_detection/utils.py
lighttext/utils/__init__.py
lightText-0.2.3.dist-info/LICENSE
lightText-0.2.3.dist-info/METADATA
lightText-0.2.3.dist-info/WHEEL
lightText-0.2.3.dist-info/top_level.txt
lightText-0.2.3.dist-info/RECORD
