Metadata-Version: 2.1
Name: lightText
Version: 0.2.3
Summary: lightsmile's text library
Home-page: https://github.com/smilelight/lightText
Author: lightsmile
Author-email: iamlightsmile@gmail.com
License: Apache-2.0
Platform: UNKNOWN
Classifier: Development Status :: 4 - Beta
Classifier: Operating System :: OS Independent
Classifier: Intended Audience :: Developers
Classifier: Programming Language :: Python
Classifier: Programming Language :: Python :: 3
Classifier: Programming Language :: Python :: 3.4
Classifier: Programming Language :: Python :: 3.5
Classifier: Programming Language :: Python :: 3.6
Classifier: Programming Language :: Python :: 3.7
Classifier: Topic :: Software Development :: Libraries
Requires-Dist: lightUtils (>=0.1.10.0)
Requires-Dist: tqdm (>=4.28.1)
Requires-Dist: jieba (>=0.39)
